{
  "项目": "哪吒知识图谱构建",
  "阶段": "阶段二：命名实体识别与关系抽取",
  "实体识别": {
    "人物": [
      "哪吒",
      "李靖",
      "殷夫人",
      "太乙真人",
      "敖丙",
      "龙王",
      "申公豹",
      "石矶娘娘",
      "杨戬",
      "雷震子",
      "姜子牙",
      "金吒",
      "木吒",
      "殷郊",
      "殷洪"
    ],
    "法宝": [
      "混天绫",
      "乾坤圈",
      "风火轮",
      "火尖枪",
      "九龙神火罩"
    ],
    "地点": [
      "陈塘关",
      "东海",
      "金光洞",
      "乾元山",
      "天庭"
    ],
    "事件": [
      "哪吒降生",
      "大闹东海",
      "削骨还父",
      "莲花化身",
      "助周伐纣",
      "封神归位"
    ],
    "组织": [
      "商朝",
      "周朝",
      "天庭",
      "截教",
      "阐教"
    ]
  },
  "关系抽取": [
    [
      "哪吒",
      "父亲",
      "李靖"
    ],
    [
      "哪吒",
      "母亲",
      "殷夫人"
    ],
    [
      "哪吒",
      "兄长",
      "金吒"
    ],
    [
      "哪吒",
      "兄长",
      "木吒"
    ],
    [
      "李靖",
      "妻子",
      "殷夫人"
    ],
    [
      "哪吒",
      "师父",
      "太乙真人"
    ],
    [
      "太乙真人",
      "徒弟",
      "哪吒"
    ],
    [
      "申公豹",
      "同门",
      "太乙真人"
    ],
    [
      "哪吒",
      "朋友",
      "敖丙"
    ],
    [
      "哪吒",
      "战友",
      "杨戬"
    ],
    [
      "哪吒",
      "战友",
      "雷震子"
    ],
    [
      "杨戬",
      "战友",
      "雷震子"
    ],
    [
      "哪吒",
      "敌人",
      "龙王"
    ],
    [
      "哪吒",
      "敌人",
      "申公豹"
    ],
    [
      "哪吒",
      "敌人",
      "石矶娘娘"
    ],
    [
      "太乙真人",
      "敌人",
      "申公豹"
    ],
    [
      "哪吒",
      "对抗",
      "龙王三太子"
    ],
    [
      "哪吒",
      "击杀",
      "龙王三太子"
    ],
    [
      "哪吒",
      "对抗",
      "石矶娘娘"
    ],
    [
      "哪吒",
      "救赎",
      "敖丙"
    ],
    [
      "太乙真人",
      "复活",
      "哪吒"
    ],
    [
      "哪吒",
      "身份转变",
      "从魔童到英雄"
    ],
    [
      "敖丙",
      "关系转变",
      "从敌人到朋友"
    ],
    [
      "哪吒",
      "拥有法宝",
      "混天绫"
    ],
    [
      "哪吒",
      "拥有法宝",
      "乾坤圈"
    ],
    [
      "哪吒",
      "拥有法宝",
      "风火轮"
    ],
    [
      "哪吒",
      "拥有法宝",
      "火尖枪"
    ],
    [
      "太乙真人",
      "赐予法宝",
      "乾坤圈"
    ],
    [
      "太乙真人",
      "赐予法宝",
      "混天绫"
    ],
    [
      "李靖",
      "镇守",
      "陈塘关"
    ],
    [
      "龙王",
      "统治",
      "东海"
    ],
    [
      "太乙真人",
      "居住",
      "金光洞"
    ],
    [
      "太乙真人",
      "修行地",
      "乾元山"
    ],
    [
      "哪吒",
      "归属",
      "阐教"
    ],
    [
      "太乙真人",
      "归属",
      "阐教"
    ],
    [
      "申公豹",
      "归属",
      "截教"
    ],
    [
      "石矶娘娘",
      "归属",
      "截教"
    ],
    [
      "李靖",
      "效忠",
      "商朝"
    ],
    [
      "哪吒",
      "助战",
      "周朝"
    ]
  ],
  "事件节点": {
    "哪吒降生": {
      "时间": "商朝末年",
      "地点": "陈塘关",
      "参与者": [
        "哪吒",
        "李靖",
        "殷夫人",
        "太乙真人"
      ],
      "结果": "灵珠子转世，出生即不凡",
      "关键物品": [
        "灵珠子"
      ]
    },
    "大闹东海": {
      "时间": "七岁时",
      "地点": "东海",
      "参与者": [
        "哪吒",
        "龙王三太子",
        "龙王"
      ],
      "结果": "打死龙王三太子，抽龙筋",
      "关键物品": [
        "混天绫",
        "乾坤圈"
      ]
    },
    "削骨还父": {
      "时间": "七岁时（大闹东海后）",
      "地点": "陈塘关",
      "参与者": [
        "哪吒",
        "李靖",
        "殷夫人",
        "龙王"
      ],
      "结果": "为不连累父母，自刎谢罪，肉身毁灭",
      "关键物品": [
        "宝剑"
      ]
    },
    "莲花化身": {
      "时间": "死后三日",
      "地点": "金光洞",
      "参与者": [
        "哪吒",
        "太乙真人"
      ],
      "结果": "太乙真人用莲花莲藕重塑肉身，获得新生",
      "关键物品": [
        "莲花",
        "莲藕",
        "金丹"
      ]
    },
    "助周伐纣": {
      "时间": "商周交替时期",
      "地点": "各处战场",
      "参与者": [
        "哪吒",
        "姜子牙",
        "杨戬",
        "雷震子",
        "太乙真人"
      ],
      "结果": "立下赫赫战功，成为伐纣先锋",
      "关键物品": [
        "风火轮",
        "火尖枪",
        "九龙神火罩"
      ]
    },
    "封神归位": {
      "时间": "封神大战后",
      "地点": "天庭",
      "参与者": [
        "哪吒",
        "姜子牙",
        "玉帝"
      ],
      "结果": "被封为\"三坛海会大神\"，位列仙班",
      "关键物品": [
        "封神榜"
      ]
    }
  },
  "三元组数据": [
    [
      "哪吒",
      "父亲",
      "李靖"
    ],
    [
      "哪吒",
      "母亲",
      "殷夫人"
    ],
    [
      "哪吒",
      "兄长",
      "金吒"
    ],
    [
      "哪吒",
      "兄长",
      "木吒"
    ],
    [
      "李靖",
      "妻子",
      "殷夫人"
    ],
    [
      "哪吒",
      "师父",
      "太乙真人"
    ],
    [
      "太乙真人",
      "徒弟",
      "哪吒"
    ],
    [
      "申公豹",
      "同门",
      "太乙真人"
    ],
    [
      "哪吒",
      "朋友",
      "敖丙"
    ],
    [
      "哪吒",
      "战友",
      "杨戬"
    ],
    [
      "哪吒",
      "战友",
      "雷震子"
    ],
    [
      "杨戬",
      "战友",
      "雷震子"
    ],
    [
      "哪吒",
      "敌人",
      "龙王"
    ],
    [
      "哪吒",
      "敌人",
      "申公豹"
    ],
    [
      "哪吒",
      "敌人",
      "石矶娘娘"
    ],
    [
      "太乙真人",
      "敌人",
      "申公豹"
    ],
    [
      "哪吒",
      "对抗",
      "龙王三太子"
    ],
    [
      "哪吒",
      "击杀",
      "龙王三太子"
    ],
    [
      "哪吒",
      "对抗",
      "石矶娘娘"
    ],
    [
      "哪吒",
      "救赎",
      "敖丙"
    ],
    [
      "太乙真人",
      "复活",
      "哪吒"
    ],
    [
      "哪吒",
      "身份转变",
      "从魔童到英雄"
    ],
    [
      "敖丙",
      "关系转变",
      "从敌人到朋友"
    ],
    [
      "哪吒",
      "拥有法宝",
      "混天绫"
    ],
    [
      "哪吒",
      "拥有法宝",
      "乾坤圈"
    ],
    [
      "哪吒",
      "拥有法宝",
      "风火轮"
    ],
    [
      "哪吒",
      "拥有法宝",
      "火尖枪"
    ],
    [
      "太乙真人",
      "赐予法宝",
      "乾坤圈"
    ],
    [
      "太乙真人",
      "赐予法宝",
      "混天绫"
    ],
    [
      "李靖",
      "镇守",
      "陈塘关"
    ],
    [
      "龙王",
      "统治",
      "东海"
    ],
    [
      "太乙真人",
      "居住",
      "金光洞"
    ],
    [
      "太乙真人",
      "修行地",
      "乾元山"
    ],
    [
      "哪吒",
      "归属",
      "阐教"
    ],
    [
      "太乙真人",
      "归属",
      "阐教"
    ],
    [
      "申公豹",
      "归属",
      "截教"
    ],
    [
      "石矶娘娘",
      "归属",
      "截教"
    ],
    [
      "李靖",
      "效忠",
      "商朝"
    ],
    [
      "哪吒",
      "助战",
      "周朝"
    ],
    [
      "哪吒降生",
      "事件类型",
      "关键事件"
    ],
    [
      "哪吒降生",
      "发生时间",
      "商朝末年"
    ],
    [
      "哪吒降生",
      "发生地点",
      "陈塘关"
    ],
    [
      "哪吒降生",
      "事件结果",
      "灵珠子转世，出生即不凡"
    ],
    [
      "哪吒",
      "参与事件",
      "哪吒降生"
    ],
    [
      "哪吒降生",
      "涉及人物",
      "哪吒"
    ],
    [
      "李靖",
      "参与事件",
      "哪吒降生"
    ],
    [
      "哪吒降生",
      "涉及人物",
      "李靖"
    ],
    [
      "殷夫人",
      "参与事件",
      "哪吒降生"
    ],
    [
      "哪吒降生",
      "涉及人物",
      "殷夫人"
    ],
    [
      "太乙真人",
      "参与事件",
      "哪吒降生"
    ],
    [
      "哪吒降生",
      "涉及人物",
      "太乙真人"
    ],
    [
      "哪吒降生",
      "涉及物品",
      "灵珠子"
    ],
    [
      "大闹东海",
      "事件类型",
      "关键事件"
    ],
    [
      "大闹东海",
      "发生时间",
      "七岁时"
    ],
    [
      "大闹东海",
      "发生地点",
      "东海"
    ],
    [
      "大闹东海",
      "事件结果",
      "打死龙王三太子，抽龙筋"
    ],
    [
      "哪吒",
      "参与事件",
      "大闹东海"
    ],
    [
      "大闹东海",
      "涉及人物",
      "哪吒"
    ],
    [
      "龙王三太子",
      "参与事件",
      "大闹东海"
    ],
    [
      "大闹东海",
      "涉及人物",
      "龙王三太子"
    ],
    [
      "龙王",
      "参与事件",
      "大闹东海"
    ],
    [
      "大闹东海",
      "涉及人物",
      "龙王"
    ],
    [
      "大闹东海",
      "涉及物品",
      "混天绫"
    ],
    [
      "大闹东海",
      "涉及物品",
      "乾坤圈"
    ],
    [
      "削骨还父",
      "事件类型",
      "关键事件"
    ],
    [
      "削骨还父",
      "发生时间",
      "七岁时（大闹东海后）"
    ],
    [
      "削骨还父",
      "发生地点",
      "陈塘关"
    ],
    [
      "削骨还父",
      "事件结果",
      "为不连累父母，自刎谢罪，肉身毁灭"
    ],
    [
      "哪吒",
      "参与事件",
      "削骨还父"
    ],
    [
      "削骨还父",
      "涉及人物",
      "哪吒"
    ],
    [
      "李靖",
      "参与事件",
      "削骨还父"
    ],
    [
      "削骨还父",
      "涉及人物",
      "李靖"
    ],
    [
      "殷夫人",
      "参与事件",
      "削骨还父"
    ],
    [
      "削骨还父",
      "涉及人物",
      "殷夫人"
    ],
    [
      "龙王",
      "参与事件",
      "削骨还父"
    ],
    [
      "削骨还父",
      "涉及人物",
      "龙王"
    ],
    [
      "削骨还父",
      "涉及物品",
      "宝剑"
    ],
    [
      "莲花化身",
      "事件类型",
      "关键事件"
    ],
    [
      "莲花化身",
      "发生时间",
      "死后三日"
    ],
    [
      "莲花化身",
      "发生地点",
      "金光洞"
    ],
    [
      "莲花化身",
      "事件结果",
      "太乙真人用莲花莲藕重塑肉身，获得新生"
    ],
    [
      "哪吒",
      "参与事件",
      "莲花化身"
    ],
    [
      "莲花化身",
      "涉及人物",
      "哪吒"
    ],
    [
      "太乙真人",
      "参与事件",
      "莲花化身"
    ],
    [
      "莲花化身",
      "涉及人物",
      "太乙真人"
    ],
    [
      "莲花化身",
      "涉及物品",
      "莲花"
    ],
    [
      "莲花化身",
      "涉及物品",
      "莲藕"
    ],
    [
      "莲花化身",
      "涉及物品",
      "金丹"
    ],
    [
      "助周伐纣",
      "事件类型",
      "关键事件"
    ],
    [
      "助周伐纣",
      "发生时间",
      "商周交替时期"
    ],
    [
      "助周伐纣",
      "发生地点",
      "各处战场"
    ],
    [
      "助周伐纣",
      "事件结果",
      "立下赫赫战功，成为伐纣先锋"
    ],
    [
      "哪吒",
      "参与事件",
      "助周伐纣"
    ],
    [
      "助周伐纣",
      "涉及人物",
      "哪吒"
    ],
    [
      "姜子牙",
      "参与事件",
      "助周伐纣"
    ],
    [
      "助周伐纣",
      "涉及人物",
      "姜子牙"
    ],
    [
      "杨戬",
      "参与事件",
      "助周伐纣"
    ],
    [
      "助周伐纣",
      "涉及人物",
      "杨戬"
    ],
    [
      "雷震子",
      "参与事件",
      "助周伐纣"
    ],
    [
      "助周伐纣",
      "涉及人物",
      "雷震子"
    ],
    [
      "太乙真人",
      "参与事件",
      "助周伐纣"
    ],
    [
      "助周伐纣",
      "涉及人物",
      "太乙真人"
    ],
    [
      "助周伐纣",
      "涉及物品",
      "风火轮"
    ],
    [
      "助周伐纣",
      "涉及物品",
      "火尖枪"
    ],
    [
      "助周伐纣",
      "涉及物品",
      "九龙神火罩"
    ],
    [
      "封神归位",
      "事件类型",
      "关键事件"
    ],
    [
      "封神归位",
      "发生时间",
      "封神大战后"
    ],
    [
      "封神归位",
      "发生地点",
      "天庭"
    ],
    [
      "封神归位",
      "事件结果",
      "被封为\"三坛海会大神\"，位列仙班"
    ],
    [
      "哪吒",
      "参与事件",
      "封神归位"
    ],
    [
      "封神归位",
      "涉及人物",
      "哪吒"
    ],
    [
      "姜子牙",
      "参与事件",
      "封神归位"
    ],
    [
      "封神归位",
      "涉及人物",
      "姜子牙"
    ],
    [
      "玉帝",
      "参与事件",
      "封神归位"
    ],
    [
      "封神归位",
      "涉及人物",
      "玉帝"
    ],
    [
      "封神归位",
      "涉及物品",
      "封神榜"
    ],
    [
      "哪吒",
      "称号",
      "三坛海会大神"
    ],
    [
      "哪吒",
      "身份",
      "灵珠子转世"
    ],
    [
      "哪吒",
      "前世",
      "灵珠子"
    ],
    [
      "李靖",
      "称号",
      "托塔天王"
    ],
    [
      "太乙真人",
      "称号",
      "乾元山金光洞太乙真人"
    ],
    [
      "敖丙",
      "身份",
      "东海龙王三太子"
    ],
    [
      "混天绫",
      "类型",
      "法宝"
    ],
    [
      "混天绫",
      "功能",
      "束缚敌人"
    ],
    [
      "乾坤圈",
      "类型",
      "法宝"
    ],
    [
      "乾坤圈",
      "功能",
      "攻击武器"
    ],
    [
      "风火轮",
      "类型",
      "法宝"
    ],
    [
      "风火轮",
      "功能",
      "飞行工具"
    ],
    [
      "火尖枪",
      "类型",
      "法宝"
    ],
    [
      "火尖枪",
      "功能",
      "近战武器"
    ],
    [
      "大闹东海",
      "前因",
      "哪吒洗澡搅动东海"
    ],
    [
      "大闹东海",
      "后果",
      "削骨还父"
    ],
    [
      "削骨还父",
      "前因",
      "大闹东海"
    ],
    [
      "削骨还父",
      "后果",
      "莲花化身"
    ],
    [
      "莲花化身",
      "前因",
      "削骨还父"
    ],
    [
      "莲花化身",
      "后果",
      "助周伐纣"
    ]
  ],
  "统计信息": {
    "实体类别数": 5,
    "实体总数": 36,
    "关系数量": 39,
    "关系类型数": 25,
    "事件节点数": 6,
    "三元组总数": 136
  }
}